castep_parse/__init__.py
castep_parse/_version.py
castep_parse/readers.py
castep_parse/utils.py
castep_parse/writers.py
castep_parse-0.2.3.dist-info/LICENSE
castep_parse-0.2.3.dist-info/METADATA
castep_parse-0.2.3.dist-info/WHEEL
castep_parse-0.2.3.dist-info/top_level.txt
castep_parse-0.2.3.dist-info/RECORD
