Metadata-Version: 2.1
Name: castep-parse
Version: 0.2.3
Summary: Input file writers and output file parsers for the density functional theory code CASTEP.
Home-page: UNKNOWN
Author: Adam J. Plowman
Author-email: adam.plowman@manchester.ac.uk
License: UNKNOWN
Project-URL: Github, https://github.com/aplowman/castep-parse
Platform: UNKNOWN
Classifier: Development Status :: 4 - Beta
Classifier: Intended Audience :: Science/Research
Classifier: Topic :: Scientific/Engineering
Classifier: Programming Language :: Python :: 3.5
Classifier: Programming Language :: Python :: 3.6
Classifier: Programming Language :: Python :: 3.7
Classifier: License :: OSI Approved :: Mozilla Public License 2.0 (MPL 2.0)
Classifier: Operating System :: OS Independent
Requires-Dist: numpy
Requires-Dist: mendeleev (==0.4.5)
